utilix/__init__.py
utilix/batchq.py
utilix/config.py
utilix/install.sh
utilix/io.py
utilix/mongo_storage.py
utilix/rundb.py
utilix/scripts/__init__.py
utilix/scripts/xefind.py
utilix/shell.py
utilix/tarball.py
utilix/utils.py
utilix/x509.py
utilix-0.12.0.dist-info/METADATA
utilix-0.12.0.dist-info/WHEEL
utilix-0.12.0.dist-info/entry_points.txt
utilix-0.12.0.dist-info/RECORD
