Metadata-Version: 2.1
Name: utilix
Version: 0.12.0
Summary: User-friendly interface to various utilities for XENON users
Home-page: https://github.com/XENONnT/utilix
Author: utilix developers
Requires-Python: >=3.8,<3.13
Classifier: Development Status :: 5 - Production/Stable
Classifier: Intended Audience :: Science/Research
Classifier: License :: OSI Approved :: BSD License
Classifier: Natural Language :: English
Classifier: Programming Language :: Python :: 3
Classifier: Programming Language :: Python :: 3.8
Classifier: Programming Language :: Python :: 3.9
Classifier: Programming Language :: Python :: 3.10
Classifier: Programming Language :: Python :: 3.11
Classifier: Programming Language :: Python :: 3.12
Classifier: Programming Language :: Python :: Implementation :: CPython
Classifier: Topic :: Scientific/Engineering :: Physics
Requires-Dist: commentjson
Requires-Dist: pandas
Requires-Dist: pydantic (>=1.10,<2.0)
Requires-Dist: pymongo
Requires-Dist: requests
Requires-Dist: simple_slurm
Requires-Dist: tqdm
Project-URL: Repository, https://github.com/XENONnT/utilix
